README.rst
setup.py
brasil_municipios/__init__.py
brasil_municipios/admin.py
brasil_municipios/apps.py
brasil_municipios/models.py
brasil_municipios/management/__init__.py
brasil_municipios/management/commands/__init__.py
brasil_municipios/management/commands/loadmunicipios.py
brasil_municipios/migrations/0001_create_models.py
brasil_municipios/migrations/0002_add_state_choices.py
brasil_municipios/migrations/__init__.py
django_brasil_municipios.egg-info/PKG-INFO
django_brasil_municipios.egg-info/SOURCES.txt
django_brasil_municipios.egg-info/dependency_links.txt
django_brasil_municipios.egg-info/top_level.txt