Metadata-Version: 1.1
Name: django-brasil-municipios
Version: 0.4
Summary: A GeoDjango app with all Brazilian municipalities and their geographical polygons, with data downloaded from the IBGE (Brazilian Institute of Geography and Statistics) website.
Home-page: https://github.com/victor-o-silva/django-brasil-municipios
Author: Victor Oliveira da Silva
Author-email: victor_o_silva@hotmail.com
License: MIT
Download-URL: https://github.com/victor-o-silva/django-brasil-municipios/tarball/0.4
Platform: UNKNOWN
Classifier: Framework :: Django
Classifier: Intended Audience :: Developers
Classifier: License :: OSI Approved :: MIT License
Classifier: Programming Language :: Python
Classifier: Programming Language :: Python :: 2
Classifier: Programming Language :: Python :: 2.7
Classifier: Programming Language :: Python :: 3
Classifier: Programming Language :: Python :: 3.4
Classifier: Programming Language :: Python :: 3.5
Classifier: Topic :: Scientific/Engineering :: GIS
